{
  "type": "reworkedmetals:smelting",
  "ingredients": [
    {
      "tag": "forge:raw_ores/raw_zinc"
    },
    {
      "tag": "forge:raw_ores/raw_zinc"
    }
  ],
  "result": {
    "item": "alltheores:zinc_ingot"
  },
  "experience": 0.2,
  "smelting_time": 200,
  "stations": [
    "furnace",
    "blast_furnace"
  ],
  "conditions": [
    {
      "type": "forge:mod_loaded",
      "modid": "alltheores"
    },
    {
      "type": "reworkedmetals:config",
      "config": "ingotsRequireTwoOre"
    }
  ]
}