{
  "type": "reworkedmetals:smelting",
  "ingredients": [
    {
      "item": "reworkedmetals:raw_copper"
    },
    {
      "item": "reworkedmetals:raw_copper"
    },
    {
      "item": "reworkedmetals:raw_copper"
    },
    {
      "item": "reworkedmetals:raw_tin"
    }
  ],
  "result": {
    "item": "reworkedmetals:bronze_ingot",
    "count": 4
  },
  "experience": 0.7,
  "smelting_time": 800,
  "stations": [
    "smeltery",
    "furnace",
    "blast_furnace"
  ],
  "conditions": [
    {
      "type": "forge:not",
      "value": {
        "type": "reworkedmetals:config",
        "config": "ingotsRequireTwoOre"
      }
    }
  ]
}